Metadata-Version: 2.1
Name: tryonai
Version: 0.1.0
Summary: TryOn AI Python SDK - Use this SDK to interact with TryOn AI API. Integrate virtual try-on, model swap, outfit generation and captioning in your application.
Home-page: https://www.tryonlabs.ai
Author: TryOn AI
Author-email: contact@tryonlabs.ai
Classifier: Programming Language :: Python :: 3
Classifier: License :: OSI Approved :: MIT License
Classifier: Operating System :: OS Independent
Requires-Python: >=3.10
